setup.py
src/strippers/__init__.py
src/strippers/mixi/__init__.py
src/strippers/mixi/_diary_write.py
src/strippers/mixi/_message_read.py
src/strippers/mixi/_message_write.py
src/strippers/mixi/_profile_read.py
src/strippers/mixi/_share_write.py
src/strippers/mixi/_voice_read.py
src/strippers/mixi/_voice_write.py
src/strippers/mixi/graphapi.py
strippers.mixi.egg-info/PKG-INFO
strippers.mixi.egg-info/SOURCES.txt
strippers.mixi.egg-info/dependency_links.txt
strippers.mixi.egg-info/namespace_packages.txt
strippers.mixi.egg-info/not-zip-safe
strippers.mixi.egg-info/requires.txt
strippers.mixi.egg-info/top_level.txt