Metadata-Version: 1.0
Name: strippers.mixi
Version: 1.0
Summary: Python library for mixi Graph API
Home-page: http://pypi.python.org/pypi/strippers.mixi
Author: Tomohiro Otsuka
Author-email: t.otsuka@gmail.com
License: LGPL
Keywords: mixi oauth
Platform: UNKNOWN
Classifier: Development Status :: 5 - Production/Stable
Classifier: License :: OSI Approved :: GNU Library or Lesser General Public License (LGPL)
Classifier: Intended Audience :: Developers
Classifier: Topic :: Software Development :: Libraries :: Python Modules
Classifier: Operating System :: OS Independent
Classifier: Natural Language :: Japanese
